Workbook
Name aporte: APP!$D$16
Name patrimonio: APP!$D$19
Name qtd_anos: APP!$D$17
Name rendimento_carteira: APP!$D$12
Name salario: APP!$D$11
Name sugestao_investimento: APP!$D$13
Name taxa_mensal: APP!$D$18

Sheet APP
B10: Configurações
B11: Salário | D11: 2000
B12: Rendimento Carteira | D12: 0.006
B13: Sugestão Investimento | D13: =D11*30% -> 600
B15: Investimento Mensal
B16: * quanto investir por mês? | D16: 200
B17: * por quantos anos investir? | D17: 5
B18: * taxa de rendimento mensal? | D18: 0.01079
B19: * quanto de patrimonio terei acumulado? | D19: =FV(taxa_mensal,qtd_anos*12,aporte*-1) -> 16755.383
B20: * quanto de dividendos mensais? | D20: =patrimonio*rendimento_carteira -> 100.5323
B22: Cenários | D22: Dividendo
A23: 2 | B23: Quanto em 2 anos? | C23: =FV($D$18,$A23*12,$D$16*-1) -> 5445.5255 | D23: =C23*rendimento_carteira -> 32.673153
A24: 5 | B24: Quanto em 5 anos? | C24: =FV($D$18,$A24*12,$D$16*-1) -> 16755.383 | D24: =C24*rendimento_carteira -> 100.5323
A25: 10 | B25: Quanto em 10 anos? | C25: =FV($D$18,$A25*12,$D$16*-1) -> 48656.843 | D25: =C25*rendimento_carteira -> 291.94106
A26: 20 | B26: Quanto em 20 anos? | C26: =FV($D$18,$A26*12,$D$16*-1) -> 225039.68 | D26: =C26*rendimento_carteira -> 1350.2381
A27: 30 | B27: Quantos em 30 anos | C27: =FV($D$18,$A27*12,$D$16*-1) -> 864433.93 | D27: =C27*rendimento_carteira -> 5186.6036
B30: Perfil | C30: Conservador
B31: Valor a ser investido por mês | C31: =aporte -> 200
B34: Tipo de FII | C34: Percentual | D34: Valores
B35: Papel | C35: =VLOOKUP($C$30&"-"&B35,Dados!A:D,4,FALSE) -> 0.3 | D35: =$C$31*C35 -> 60
B36: Tijolo | C36: =VLOOKUP($C$30&"-"&B36,Dados!A:D,4,FALSE) -> 0.5 | D36: =$C$31*C36 -> 100
B37: Hibrídos | C37: =VLOOKUP($C$30&"-"&B37,Dados!A:D,4,FALSE) -> 0.1 | D37: =$C$31*C37 -> 20
B38: FOF's | C38: =VLOOKUP($C$30&"-"&B38,Dados!A:D,4,FALSE) -> 0.1 | D38: =$C$31*C38 -> 20
B39: Desenvolvimento | C39: =VLOOKUP($C$30&"-"&B39,Dados!A:D,4,FALSE) -> 0 | D39: =$C$31*C39 -> 0
B40: Hotelarias | C40: =VLOOKUP($C$30&"-"&B40,Dados!A:D,4,FALSE) -> 0 | D40: =$C$31*C40 -> 0
C41: =SUM(C35:C40) -> 1 | D41: =SUM(D35:D40) -> 200

Sheet Dados
A2: Chave | B2: Perfil | C2: tipo de fii | D2: %
A3: =B3&"-"&C3 -> Conservador-Papel | B3: Conservador | C3: Papel | D3: 0.3 | I3: %
A4: =B4&"-"&C4 -> Conservador-Tijolo | B4: Conservador | C4: Tijolo | D4: 0.5 | H4: Moderado-Tijolo | I4: =VLOOKUP(H4,$A:$D,4,FALSE) -> 0.4
A5: =B5&"-"&C5 -> Conservador-Hibrídos | B5: Conservador | C5: Hibrídos | D5: 0.1
A6: =B6&"-"&C6 -> Conservador-FOF's | B6: Conservador | C6: FOF's | D6: 0.1
A7: =B7&"-"&C7 -> Conservador-Desenvolvimento | B7: Conservador | C7: Desenvolvimento | D7: 0
A8: =B8&"-"&C8 -> Conservador-Hotelarias | B8: Conservador | C8: Hotelarias | D8: 0
A9: =B9&"-"&C9 -> Moderado-Papel | B9: Moderado | C9: Papel | D9: 0.32
A10: =B10&"-"&C10 -> Moderado-Tijolo | B10: Moderado | C10: Tijolo | D10: 0.4
A11: =B11&"-"&C11 -> Moderado-Hibrídos | B11: Moderado | C11: Hibrídos | D11: 0.08
A12: =B12&"-"&C12 -> Moderado-FOF's | B12: Moderado | C12: FOF's | D12: 0.1
A13: =B13&"-"&C13 -> Moderado-Desenvolvimento | B13: Moderado | C13: Desenvolvimento | D13: 0.1
A14: =B14&"-"&C14 -> Moderado-Hotelarias | B14: Moderado | C14: Hotelarias | D14: 0
A15: =B15&"-"&C15 -> Agressivo-Papel | B15: Agressivo | C15: Papel | D15: 0.5
A16: =B16&"-"&C16 -> Agressivo-Tijolo | B16: Agressivo | C16: Tijolo | D16: 0.1
... A20: =B20&"-"&C20 -> Agressivo-Hotelarias | B20: Agressivo | C20: Hotelarias | D20: 0.1

Sheet Planilha3
